nunc/__init__.py
nunc-0.0.1.dist-info/LICENSE.txt
nunc-0.0.1.dist-info/METADATA
nunc-0.0.1.dist-info/WHEEL
nunc-0.0.1.dist-info/top_level.txt
nunc-0.0.1.dist-info/RECORD
